{"code":200,"data":{"pageNo":1,"pageSize":6,"totalCount":149,"list":[{"channelId":110,"comments":566,"contentId":"3480568","cover":"http://cdn.aixifan.com/dotnet/20120923/style/image/cover-day.png","description":"共享单车，真是一面国民照妖镜","isArticle":1,"isRecommend":0,"releaseDate":1487323628000,"stows":293,"tags":["共享单车"],"title":"共享单车，真是一面国民照妖镜","toplevel":1,"user":{"userImg":"http://cdn.aixifan.com/dotnet/artemis/u/cms/www/201702/11095238c8k690tf.jpg","userId":458735,"username":"栀颜丶"},"viewOnly":0,"views":95685},{"channelId":110,"comments":446,"contentId":"3480043","cover":"http://cdn.aixifan.com/dotnet/20120923/style/image/cover-day.png","description":"悉尼海鲜店被罚款, 因为没有用人道的方式宰杀龙虾 [澳大利亚媒体]","isArticle":1,"isRecommend":0,"releaseDate":1487314031000,"stows":165,"tags":["悉尼海鲜店被罚款","因为没有用人道的方式宰杀龙虾","[澳大利亚媒体]"],"title":"悉尼海鲜店被罚款, 因为没有用人道的方式宰杀龙虾 [澳大利亚媒体]","toplevel":1,"user":{"userImg":"http://cdn.aixifan.com/dotnet/artemis/u/cms/www/201507/04102521q7de.jpg","userId":290374,"username":"少泊"},"viewOnly":0,"views":68155},{"channelId":110,"comments":379,"contentId":"3480024","cover":"http://cdn.aixifan.com/dotnet/20120923/style/image/cover-day.png","description":"长城昨日在美举办首映礼，并于今日开始上映。文章转自游民星空。","isArticle":1,"isRecommend":0,"releaseDate":1487313591000,"stows":100,"tags":["长城","烂番茄","Metacritic"],"title":"电影《长城》海外口碑：烂番茄新鲜度34% metacritic评分35分","toplevel":1,"user":{"userImg":"http://cdn.aixifan.com/dotnet/artemis/u/cms/www/201308/22171543tkfw.jpg","userId":642684,"username":"威克斯勋爵"},"viewOnly":0,"views":54754},{"channelId":110,"comments":260,"contentId":"3481290","cover":"http://cdn.aixifan.com/dotnet/20120923/style/image/cover-night.png","description":"12岁结婚14岁生女 重庆“童养媳”悲惨遭遇谁买单？","isArticle":1,"isRecommend":0,"releaseDate":1487334724000,"stows":86,"tags":["童养媳"],"title":"12岁结婚14岁生女 重庆“童养媳”悲惨遭遇谁买单？","toplevel":1,"user":{"userImg":"http://cdn.aixifan.com/dotnet/artemis/u/cms/www/201611/04234355kwxzqpd2.jpg","userId":5950045,"username":"千面无貌血舌暗夜咆哮之神"},"viewOnly":0,"views":40707},{"channelId":110,"comments":134,"contentId":"3480533","cover":"http://cdn.aixifan.com/dotnet/20120923/style/image/cover-day.png","description":"那个男的真的是丧心病狂啊。","isArticle":1,"isRecommend":0,"releaseDate":1487323257000,"stows":105,"tags":["苏州","换成","强吻","大爷","大妈","地铁站","保洁员","保洁"],"title":"苏州保洁员地铁站被强吻后 保洁大妈已换成保洁大爷","toplevel":1,"user":{"userImg":"http://cdn.aixifan.com/dotnet/artemis/u/cms/www/201510/250122196mllhdfz.jpg","userId":370283,"username":"亲切的人可信兄弟"},"viewOnly":0,"views":38960},{"channelId":110,"comments":288,"contentId":"3480695","cover":"http://cdn.aixifan.com/dotnet/20120923/style/image/cover-day.png","description":"关于中国诗词，外国网友讨论最多的是能否帮助学习汉语","isArticle":1,"isRecommend":0,"releaseDate":1487325454000,"stows":317,"tags":["诗词"],"title":"关于中国诗词，外国网友讨论最多的是能否帮助学习汉语","toplevel":1,"user":{"userImg":"http://cdn.aixifan.com/dotnet/artemis/u/cms/www/201611/25225932fzgly33u.jpg","userId":3328282,"username":"寄昙说"},"viewOnly":0,"views":34041}]},"message":"OK"}